dst_conversion_package/__init__.py
dst_conversion_package/__main__.py
dst_conversion_package/explorer.py
cdef_dst_conversion-0.1.0.dist-info/METADATA
cdef_dst_conversion-0.1.0.dist-info/WHEEL
cdef_dst_conversion-0.1.0.dist-info/entry_points.txt
cdef_dst_conversion-0.1.0.dist-info/top_level.txt
cdef_dst_conversion-0.1.0.dist-info/RECORD
