Metadata-Version: 2.4
Name: cdef-dst-conversion
Version: 0.1.0
Summary: A tool for exploring and converting SAS7BDAT files to Parquet.
Author-email: Tobias Kragholm <your.email@example.com>
Classifier: Programming Language :: Python :: 3
Classifier: License :: OSI Approved :: MIT License
Classifier: Operating System :: OS Independent
Requires-Python: >=3.12
Requires-Dist: polars
Requires-Dist: pyreadstat
